django_db_log/__init__.py
django_db_log/admin.py
django_db_log/apps.py
django_db_log/handlers.py
django_db_log/models.py
django_db_log/settings.py
django_db_log/tasks.py
django_db_log/urls.py
django_db_log/views.py
django_db_log/migrations/0001_initial.py
django_db_log/migrations/0002_auto_20180829_1626.py
django_db_log/migrations/0003_auto_20180829_1630.py
django_db_log/migrations/__init__.py
django_db_log/static/css/django_db_log.css
django_db_log/static/js/django_db_log.js
django_db_log/templates/django_db_log/base.html
django_db_log_plugin-0.1.3.dist-info/METADATA
django_db_log_plugin-0.1.3.dist-info/RECORD
django_db_log_plugin-0.1.3.dist-info/WHEEL
django_db_log_plugin-0.1.3.dist-info/top_level.txt
tests/__init__.py
tests/settings.py
tests/test_models.py
tests/urls.py
