Metadata-Version: 2.1
Name: django-db-log-plugin
Version: 0.1.3
Summary: Custom DB Log Handler for Django Projects.
Home-page: https://github.com/eduarde/django_db_log
Author: Eduard Erja
Author-email: eduard.erja@gmail.com
License: MIT
Keywords: django_db_log
Platform: UNKNOWN
Classifier: Development Status :: 3 - Alpha
Classifier: Framework :: Django :: 1.11
Classifier: Framework :: Django :: 2.0
Classifier: Intended Audience :: Developers
Classifier: License :: OSI Approved :: BSD License
Classifier: Natural Language :: English
Classifier: Programming Language :: Python :: 2
Classifier: Programming Language :: Python :: 2.7
Classifier: Programming Language :: Python :: 3
Classifier: Programming Language :: Python :: 3.4
Classifier: Programming Language :: Python :: 3.5
Classifier: Programming Language :: Python :: 3.6
Requires-Dist: django-apscheduler (==0.2.13)
